[
  {
    "thumbnail": "https://i.imgur.com/QDLI6pG_d.webp?maxwidth=640&shape=thumb&fidelity=medium",
    "title": "JUFE-210mmsub*vip",
    "info": "မြန်မာစာတန်းထိုးအဖိုးတို့ မာယာ သဲကိုးဖြာအဖိုးကြီးတစ်ယောက်နဲ့ နွေရာသီကျောင်းပိတ်ရက် အိမ်အလည်ပြန်လာတဲ့ မြေးအရွယ် ကလေးမလေးတစ်ယောက်တို့ကြားက အဖြစ်အပျက်ကလေးပဲဖြစ်ပါတယ်အဖိုးနဲ့မတွေ့တာကြာတဲ့ ဟိုဘက်အိမ်က ကလေးမလေး နွေရာသီကျောင်းပိတ်ရက် အလည်ပြန်လာတော့ အရင်လိုကလေးမဟုတ်တော့ဘဲ မျက်စိရှေ့တင် ထွားလာတာကိုတွေ့ရတော့ အရမ်းအံ့သြမိပါတယ် မင်းသမီးနာမည် Oka Erina",
    "url": "https://www.mediafire.com/file/1if02qavxil7gjm/JUFE_210_-SD.mp4/file"
  },
  {
    "thumbnail": "https://i.imgur.com/uvBZgRp_d.webp?maxwidth=640&shape=thumb&fidelity=medium",
    "title": "MIDV-021mmsub*vip",
    "info": "မြန်မာစာတန်းထိုးသူဌေးသမီးရိုစီ‌လေးဟာ ကျောင်းတုန်းကဆရာနဲ့ အမှတ်မထင်ပြန်တွေ့တော့ အိမ်ထောင်ရေးအဆင်မပြေတာတွေကိုပြောပြရင်း ဆရာကနှစ်သိမ့်ပေးလိုက်ပါတယ် ဘယ်လိုနှစ်သိမ့်ပေးမှာလဲဆိုတာကတော့ ကိုယ်တိုင်ကြည့်ရှုပါ...မင်းသမီးနာမည် Tsubomi",
    "url": "https://www.mediafire.com/file/tzojnewbi8369s0/MIDV-021.mp4/file"
  },
  {
    "thumbnail": "https://i.imgur.com/4qu3eeO_d.webp?maxwidth=640&shape=thumb&fidelity=medium",
    "title": "CAWD-271mmsub*vip",
    "info": "မြန်မာစာတန်းထိုးကုမ္ပဏီမှာ တလွဲလုပ်လို့ ခဏခဏ အဆူခံရတဲ့သူမကို ဘောစိက အားပေးရာကနေ ခင်မင်သွားခဲ့ကြပါတယ် ကုမ္ပဏီကလူတွေအကုန်ဆိုင်မှာသွားသောက်ကြပေမယ့် တစ်ဦးတည်းသော မိန်းကလေးဖြစ်တဲ့သူမက အသောက်နိုင်ဆုံးဆုကို ရရှိခဲ့ပြီး မှောက်အောင်သောက်ခဲ့ရာမှ ဘောစိနဲ့ ဟိုတယ်မှာကိုကာကိုလာသွားသောက်ခဲံကြပါတော့တယ်.... မင်းသမီးနာမည် Misono Mizuhara",
    "url": "https://www.mediafire.com/file/1r9lkaf8ku1ym6j/CAWD_271_-SD.mp4/file"
  },
  {
    "thumbnail": "https://i.imgur.com/bGvWirJ_d.webp?maxwidth=640&shape=thumb&fidelity=medium",
    "title": "JUL-940mmsub*vip",
    "info": "မြန်မာစာတန်းထိုးအိမ်လာလည်တဲ့ သားဖစ်သူရဲ့ သူငယ်ချင်းကို ချာတိတ်လေးဆိုပီး ဆွဲစားမလို့ လုပ်နေတဲ့ အန်တီAsahiကောင်လေးကတော့ သတိပေးရှာပါတယ် ပစ္စည်းကြီးလို့ မိန်းကလေးတိုင်းထွက်ပြေးတယ်လို့ ဘာဆက်ဖစ်မလဲဆိုတာကိုတော့ ဇာတ်လမ်းတွင်ကြည့်ရှုလိုက်ပါမင်းသမီးနာမည် Asahi Mizuno",
    "url": "https://www.mediafire.com/file/wvefuybzo5hd5um/JUL-940.mp4/file"
  },
  {
    "thumbnail": "https://i.imgur.com/VO0HjWb_d.webp?maxwidth=640&shape=thumb&fidelity=medium",
    "title": "ADN-231mmsub*vip",
    "info": "မြန်မာစာတန်းထိုးခင်ပွန်းဖစ်သူရဲ့ အချစ်ဆုံးသူငယ်ချင်း လို့ဆိုတဲ့သူက ကျမကို ခင်ပွန်းမသိချိန်မှာ လာလိုးတယ်ဒါလား အချစ်ဆုံးသူငယ်ချင်း..ကျေးဇူးပြု၍ ငါ့ကိုခွင့်လွတ်ပါ ယောကျာ်းငါဘယ်လိုမှ ရုန်းမထွက်နိုင်ခဲ့လို့ပါမင်းသမီးနာမည် Yuka Arai",
    "url": "https://www.mediafire.com/file/bpodxftzlcuzn62/ADN-231.mp4/file"
  },
  {
    "thumbnail": "https://i.imgur.com/elWIiJn_d.webp?maxwidth=640&shape=thumb&fidelity=medium",
    "title": "HMN-094mmsub*vip",
    "info": "မြန်မာစာတန်းထိုးMC တစ်ယောက် sex chat တဲ့ app တစ်ခုမှာ နာမည်ကြီးနေတဲ့ သူငယ်ချင်းအမေကို တွေ့လိုက်ရပါတယ် သူငယ်ချင်းအမေ အန်တီနဲ့ sex chat ရင်းအားမရတော့ဘဲ အပြင်မှာ ကော်ဖီဒိတ်ကြပြီးနောက် ဟိုတယ်မှာကိုကာကိုလာသောက်ဖို့ တစ်ပါတည်း ခေါ်သွားခဲ့ပါတယ် နောက်ပိုင်းမှာ သူငယ်ချင်းဆီကို သွားဆော့သလိုလိုနဲ့ သူငယ်ချင်းအမေ အန်တီ နဲ့ သွားသွားဆော့နေပါတော့တယ်.....မင်းသမီးနာမည် Ai Sayama",
    "url": "https://www.mediafire.com/file/6jj53qfbvdj8fez/HMN_094_-SD.mp4/file"
  },
  {
    "thumbnail": "https://i.imgur.com/h5wNwBI_d.webp?maxwidth=640&shape=thumb&fidelity=medium",
    "title": "RBD-756mmsub*vip",
    "info": "မြန်မာစာတန်းထိုးမုဒိန်းကောင်တွေကို မုန်းတီးပီး တရားမျှတမှုကိုသာမြတ်နိုးတဲ့ အမျိုးသမီးရှေ့နေသည် မုဒိမ်းကျင့်ခံရသူဖြစ်လာသည်  အကူအညီမရှိ၊ မျှော်လင့်ချက်မရှိ...မင်းသမီးနာမည် Nanami Kawakami",
    "url": "https://www.mediafire.com/file/mcy3kzicp0knhgy/RBD-756.mp4/file"
  },
  {
    "thumbnail": "https://i.imgur.com/Eoo9ky9_d.webp?maxwidth=640&shape=thumb&fidelity=medium",
    "title": "ATID-471mmsub*vip",
    "info": "မြန်မာစာတန်းထိုးမိမိ ကြွေနေတဲ့ ကောင်လေးကို ဖြတ်လုပီး စနှိုက်ကျော်သွားတဲ့ ကောင်မကို လူမည်းခေါ်ကာ လက်စားချေခိုင်းခဲ့ရာ....မင်းသမီးနာမည် Ichika Matsumoto",
    "url": "https://www.mediafire.com/file/beyhczbqm9b0nyj/ATID_471_-SD.mp4/file"
  },
  {
    "thumbnail": "https://i.imgur.com/Bcmr5EN_d.webp?maxwidth=640&shape=thumb&fidelity=medium",
    "title": "JUL-019mmsub*vip",
    "info": "မြန်မာစာတန်းထိုးတောင်ပေါ်သားလေးကတော့ အဆောင်ပြန်လည်းလုပ်စရာမရှိတာမို့ သူများအလုပ်တခုကိုအစားထိုးလုပ်ပေးနေပါတယ် ယု ရှိနိုဒ ကတော့ ချိန်းထားတဲ့အလုပ်ကိစ္စတခုရှိလို့ သွားတွေ့ရင်း မိုးသည်းလို့ ကုမ္ပဏီကိုပြန်လာတဲ့ မိုးရေတွေ စိုကုန်ပါတော့တယ် မင်းသမီးနာမည် Yu Shinoda",
    "url": "https://www.mediafire.com/file/ce4bzwmxxxu2a6o/JUL-019.mp4/file"
  },
  {
    "thumbnail": "https://i.imgur.com/O9yAggw_d.webp?maxwidth=640&shape=thumb&fidelity=medium",
    "title": "MEYD-121mmsub*vip",
    "info": "မြန်မာစာတန်းထိုးညီဖြစ်သူရဲ့မိန်းမကို တစ်ဖက်သတ်ကြိတ်ကြွေနေတဲ့ အကိုကြီးတစ်ယောက်ရဲ့ဇာတ်လမ်းလေးပါမင်းသမီးနာမည် Asahi Mizuno",
    "url": "https://www.mediafire.com/file/fnxjfqhrftj5tp8/MEYD+121.mp4/file"
  },
  {
    "thumbnail": "https://i.imgur.com/8znqY3G_d.webp?maxwidth=640&shape=thumb&fidelity=medium",
    "title": "HOKS-001mmsub*vip",
    "info": "မြန်မာစာတန်းထိုးအရက်သောက်စမရှိတဲ့သူမဟာ ခါးသက်တဲ့အရက်ကို ကျိတ်မှိတ်မြိုချရင်း အရမ်းထန်လာပြီး မမြိုချသင့်တာ မြိုချမိသွားခဲ့ပါတယ် မင်းသမီးနာမည် Satomi Suzuki",
    "url": "https://www.mediafire.com/file/1s4yantlghhbg3z/HOKS_001-SD.mp4/file"
  },
  {
    "thumbnail": "https://i.imgur.com/wyqtZLt_d.webp?maxwidth=640&shape=thumb&fidelity=medium",
    "title": "JUL-684mmsub*vip",
    "info": "မြန်မာစာတန်းထိုးကြောင်ခံတွင်းပျက် အဖိုးကြီးနဲ့ ဇရက်တောင်ပံကျိုး ယောဂဆရာမလေး...အဖိုးကြီးက ကျန်းမာရေးမလိုက်စားပါဘူး ဒါကြောင့် မိန်းမက ယောဂကျင့်ဖို့အတင်းခေါ်မိရာက ဆရာမလေးနဲ့ ဘယ်လိုတွေပွဲကြမ်းကြမလား နှစ်ဦးနှစ်ဖက်က အိမ်ထောင်သည်တွေဆိုတော့ သူတို့တွေမသိအောင် ဘယ်လိုတွေခိုးစားမလဲဆိုတာကတော့...မင်းသမီးနာမည် Sakuraka Mitsuki",
    "url": "https://www.mediafire.com/file/wrn6h3uszbvklhu/JUL-684.mp4/file"
  },
  {
    "thumbnail": "https://i.imgur.com/j6VsEig_d.webp?maxwidth=640&shape=thumb&fidelity=medium",
    "title": "MUDR-010mmsub*vip",
    "info": "မြန်မာစာတန်းထိုးရထားစီးတဲ့ နာမည်ကြီး manga တစ်ခုကို ပြန်ရိုက်ထားတဲ့ကားလေးပါ အထက်တန်းကျောင်းသူလေးတစ်ယောက်ဟာ ရထားစီးရင်း ဦးလေးကြီးနဲ့ တွေ့ဆုံပြီးနောက်..မင်းသမီးနာမည် Koharu Suzuki",
    "url": "https://www.mediafire.com/file/kcrp6jrvi8wyyj9/MUDR_010-SD.mp4/file"
  },
  {
    "thumbnail": "https://i.imgur.com/m8vMjCB_d.webp?maxwidth=640&shape=thumb&fidelity=medium",
    "title": "ADN-146mmsub*vip",
    "info": "မြန်မာစာတန်းထိုးအစကတော့ အနှိပ်သည်အကြောပြင်ဆရာခေါ်တာ သူမအမျိုးသားအတွက်ဖြစ်ပေမယ့် နောက်ပိုင်းမှာ သူမပါအနှိပ်ခံလာပြီး...တစ်ခါခံပြီး နောက်ထပ်မခံရမနေနိုင်အောင်ဖြစ်ခဲ့ရသော ...ထိမိဂွိလှသော အကြောပြင်ဆရာရဲ့ အနှိပ်ကွက်တွေဟာ...မင်းသမီးနာမည် Saki Okuda",
    "url": "https://www.mediafire.com/file/bwfmjg7cidpviu2/ADN_146_-SD.mp4/file"
  },
  {
    "thumbnail": "https://i.imgur.com/SGpyYpl_d.webp?maxwidth=640&shape=thumb&fidelity=medium",
    "title": "PRED-086mmsub*vip",
    "info": "မြန်မာစာတန်းထိုးချစ်သူကောင်လေးနဲ့တွေ့ဖို့ ညဘက် bus ကား စီးရာကနေ ကားပေါ်မှာဦးလေးကြီးတစ်ယောက်ရဲ့ ဝိုက်တာကိုခံလိုက်ရတဲ့ မိန်းမပျိုလေးမင်းသမီးနာမည် Riona Minami",
    "url": "https://www.mediafire.com/file/k98yh4z9bw6yu4d/PRED-086.mp4/file"
  },
  {
    "thumbnail": "https://i.imgur.com/3KYjqIg_d.webp?maxwidth=640&shape=thumb&fidelity=medium",
    "title": "JUX-773mmsub*vip",
    "info": "မြန်မာစာတန်းထိုးယောက္ခမ နဲ့ တစ်ထောင့်တစ်ညရွာမှာရှိတဲ့ ယောက်ျားလေး တစ်၀က်လောက်က FA တွေဖြစ်ကြပြီး တစ်နေ့မှာတော့ ရွာကို အကိတ်မလေးတစ်ယောက် ရောက်လာခဲ့ပါတယ် အကြောင်းရင်းကတော့ ရွာသားတစ်ယောက်နဲ့ လက်ထပ်ပြီး ပါလာတာဖြစ်ပါတယ် အရမ်းကိတ်တဲ့ သူမကို FA တွေက ကြိုဆိုကြရုံမက သူမယာက္ခထီးမုဆိုးဖိုကြီးကဆိုရင် မျက်စိအောက်ကကို အပျောက်မခံတော့ပါဘူး နောက်ပိုင်းမှာ ဘာတွေဆက်ဖြစ်မလဲဆိုတာကတော့......မင်းသမီးနာမည် Chitose Saegusa",
    "url": "https://www.mediafire.com/file/4etorb1e55r1113/JUX+773-SD.mp4/file"
  },
  {
    "thumbnail": "https://i.imgur.com/dgHXayp_d.webp?maxwidth=640&shape=thumb&fidelity=medium",
    "title": "JUL-802mmsub*vip",
    "info": "မြန်မာစာတန်းထိုးဇာတ်လမ်းအစကို မလိနာတို့လင်မယားနှစ်ယောက်အောင်ပွဲခံနေတာနဲ့ စထားပါတယ်...မလိနာယောကျာ်း နိုင်ငံခြားကုမ္ပဏီမှာအလုပ်ရသွားလို့ပါ...အလုပ်ထဲဝင်ခါစအခက်တွေ့နေတုန်း နိုင်ငံခြားသားဂျွန်နီက ကူညီပေးခဲ့တော့ ဘော်ဒါတွေဖြစ်သွားပြီး အိမ်ကိုထမင်းစားဖိတ်မိရာကနေ  I LOVE U တွေဖြစ်ကုန်ပီး #Decensored နဲ့ ကြည့်ရှု့ခံစားလိုက်ပါ...မင်းသမီးနာမည် Marina Shiraishi",
    "url": "https://www.mediafire.com/file/19sq6j55zq6jls8/JUL-802.mp4/file"
  },
  {
    "thumbnail": "https://i.imgur.com/elqBo9J_d.webp?maxwidth=640&shape=thumb&fidelity=medium",
    "title": "SHKD-512mmsub*vip",
    "info": "မြန်မာစာတန်းထိုးမြန်မာပရိသတ်တွေရဲ့ အကြိုက် ရေပိုက်ပြင်တဲ့ဇာတ်လမ်းလေးပါရေပိုက်ပြင်ရင်း အတွင်းခံခိုးသွားတဲ့ အကိုကြီးနဲ့ အိမ်ရှင်မလေး Misaki တို့ကြား ပြင်းထန်တဲ့ တိုက်ပွဲတွေကို ကြည့်ရှုရပါမယ်မင်းသမီးနာမည် Misaki Honda",
    "url": "https://www.mediafire.com/file/g2fo1ok1gwsq12n/SHKD_512-SD.mp4/file"
  },
  {
    "thumbnail": "https://i.imgur.com/cARqu5B_d.webp?maxwidth=640&shape=thumb&fidelity=medium",
    "title": "DASD-697mmsub*vip",
    "info": "မြန်မာစာတန်းထိုးဘောင်းဘီအမြဲတမ်းကျပ်နေတတ်တဲ့ ကိုလူမည်းနဲ့ အရမ်းချစ်စရာကောင်းပြီး ဖလန်းဖလန်းထတဲ့ ဆယ်ကျော်သက်အရွယ်ကောင်မလေးတစ်ယောက်အကြောင်းပါကောင်မလေးက ရည်းစားရှိပြီး ကိုလူမည်းနဲ့ အခန်းချင်းကပ်ရက်မှာ သူ့ဘဲနဲ့အတူတူနေထိုင်ပါတယ်...မင်းသမီးနာမည် Yui Nagase",
    "url": "https://www.mediafire.com/file/vu8bbpqa4srjdv3/DASD_697-SD.mp4/file"
  },
  {
    "thumbnail": "https://i.imgur.com/0v7iGlB_d.webp?maxwidth=640&shape=thumb&fidelity=medium",
    "title": "SNIS-191mmsub*vip",
    "info": "မြန်မာစာတန်းထိုးအလုပ်မှာ အမြဲဆူလေ့ရှိသော ဌာနမူးမမတစ်ယောက် ရထားပေါ်မှာ ဖင်နှိုက်ခံနေရတာကို တွေ့လိုက်ရတဲ့အခါ...ဘာဆက်ဖစ်မှာလဲမင်းသမီးနာမည် Kirara Asuka",
    "url": "https://www.mediafire.com/file/hwwtfw1zcht9bs3/SNIS-191.mp4/file"
  }
]