[
  {
    "thumbnail": "https://imgs1cdn.adultempire.com/products/33/3190933h.jpg",
    "title": "Our Babysitter Does Anal 3 *vip",
    "info": "Actors: Ava Sinclaire, Derrick Pierce, Donny Sins, Izzy Lush, Keira Croft, Maddy May, Mike Mancini, Ryan McLaneCountry: USADuration: 01:50:25Quality: DVD ,Release: 2021",
    "url": "https://5.mangovideo.pw/contents/videos//51000/51787/51787.mp4"
  },
  {
    "thumbnail": "https://i.pinimg.com/originals/ef/22/10/ef2210dba9ca52a060d3727e01624193.jpg",
    "title": "Monamour (2006)mmsub *vip",
    "info": "ရှေးလူကြီးများကပြောကြပါတယ်အိမ်ထောင်ရေးမှာ အိပ်ယာပေါ်မှာမသာယာနိုင်ရင်အပြင်မှာလဲအဆင်မပြေနိုင်ပါဘူးတဲ့။ဒီဇာတ်ကားဟာအိမ်ထောင်ရေး သုခမပြည့်စုံလို့မိန်းမဖြစ်သူကတစိမ်းယောင်္ကျားတစ်ယောက်အပေါ်မှာစိတ်ဖောက်ပြန်တဲ့အချစ်ဇတ်လမ်းလေးပါယောင်္ကျားဖြစ်သူဟာလဲအလုပ်နှင့်လူမှုရေးတွေမှာသာအားဖြည့်ပေမယ့်အိမ်ကအိပ်ယာပေါ်မှာတော့ ကျရှုံးသူတစ်ဦးဖြစ်နေပါတယ်။အချစ်နဲ့ကာမတက်မက်မှုကရောထွေးလျက်ရှိပြီးတကယ်မချစ်လဲတက်မက်မှုနောက်လိုက်ရင်းလမ်းမှားရောက်သွားတက်ကြတာပါပဲ။မိန်းမတွေရဲ့တကယ့်လိုအင်ဆန္ဒကိုဖြည့်ဆည်းနိုင်ဖို့ဘာတွေလုပ်သင့်လဲဆိုတာကိုဒီရုပ်ရှင်ကားကိုကြည့်ရင်းနဲ့သဘောပေါက်နိုင်မှာပါ။ဒီဇာတ်ကားကိုမိသားစုနှင့်ကလေးသူငယ်များရှေ့တွင်မကြည့်ပါနှင့်အရွယ်မရောက်သေးသူများကြည့်ရှုရန်မသင့်တော်ပါ။18+R အဆင့်ဖြစ်ပါ၍ဆင်ဆာဖြတ်ထားမည်မဟုတ်ပါ",
    "url": "http://www.mediafire.com/file/pcepznu9hvoymag/Monamour+(2006).mp4/file"
  },
  {
    "thumbnail": "https://www.familyvideo.com/media/catalog/product/W/D/WDM_DREG2210D.jpg",
    "title": "Kiss and Kill (2017)mmsub *vip",
    "info": "ဇာတ်ကားကတော့18+ half movies ဆန်ဆန်ရိုက်ထားပေမဲ့ ဇာတ်လမ်းကောင်းတဲ့ ဇာတ်ကားလေးတစ်ကားပါ ဟားရစ် နဲ့ ကေသီ တို့က လင်မယားတွေ ဖြစ်ကြပေမဲ့ တစ်ဦးနဲ့တစ်ဦးတော့ ရောရောနှောနှော သိပ်မနေဖြစ်ခဲ့ကြဘူး ဟားရစ် ကလဲ အလုပ်ရှိတယ်လို့အကြောင်းပြပြီး ကေသီ နဲ့ အတူတူအိမ်မှာ သိပ်နေလေ့မရှိပါဘူး အဲဒါနဲ့ တစ်ညမှာ ကေသီ က စိတ်ထွက်ပေါက်အနေနဲ့ ဘားဆိုင်မှာ ယောက်ျားတစ်ယောက် မက် နဲ့အတူတူဖြတ်သန်းခဲ့တယ် မက် နဲ့ ကေသီ တို့နှစ်ယောက်ရဲ့ ပုံကို ဂျန် က ယူပြီး ကေသီ ကို ခြိမ်းခြောက်ပါတော့တယ် လိုချင်တာတွေ တောင်းပါတော့တယ် တစ်ညမှာ မက် နဲ့ ကေသီ တို့နှစ်ယောက်ဆုံပြီး မက် က ကေသီကို သေနတ်ပေးပြီး ဂျန် ကို သတ်ဖို့ ခိုင်းခဲ့တယ် ကေသီ က ဂျန် တို့အိမ်ရောက်တော့ ဂျန်နဲ့အတူ သူ့ယောက်ျား ဟားရစ် နဲ့ ဖောက်ပြန်နေတာ တွေ့လိုက်ရလို့ နှစ်ယောက်လုံးကို သတ်လိုက်ပါတော့တယ် နောက်တော့ မက် ကလဲ ဟားရစ်ကို ထပ်လှည့်စားဖို့ကြိုးစားခဲ့ပေမဲ့ မက် ကိုအဆိပ်ခပ်ပြီး သတ်လိုက်တယ် ဒါမဲ့ နောက်ဆုံးမှာတော့ လူသတ်သမားက ဟားရစ် ဆိုတာ ဘယ်သူမှ မသိခဲ့ကြပါဘူး အပြည့်အစုံကို ကြည့်ရှုလိုက်ကြပါ",
    "url": "http://www.mediafire.com/file/yt8b687rrlk9o73/28_kiss_and_kill_-_451_MB.mp4/file"
  },
  {
    "thumbnail": "https://imgs1cdn.adultempire.com/products/46/1700646h.jpg",
    "title": "Football Players Wives *vip",
    "info": "Football Players Wivesmmsub မဟုတ်ပေမယ့် အကြိုက်တေါ့မယ် ထင်ပါတယ်",
    "url": "https://www.mediafire.com/file/p2m680juzqv6kxb/%255BDynamite_Channel%255DFootball_Players%2527_Wives.mp4/file"
  },
  {
    "thumbnail": "https://www.themoviedb.org/t/p/w220_and_h330_face/buCvrlg52ZWsXIPJlOpe8m3r4sv.jpg",
    "title": "Little Girl Blue *vip",
    "info": "ဇာတ်လမ်းကတော့အရမ်းခန့်ကြတဲ့ဆရာတွေနဲ့အရမ်းလှကြတဲ့ကျောင်းသူလေးတွေရဲ့လူငယ်ဘဝကျောင်းကြီးမှာလွတ်လွတ်လပ်လပ်ပျော်ရွှင်မှုတွေနဲ့သာယာမှုတွေကိုဖော်ပြထားတဲ့အတွက်အရမ်းကောင်းတဲ့ကားတစ်ကားဖြစ်ပါတယ်နော်....",
    "url": "https://www.mediafire.com/file/9utjgcubrdhngor/%255BDynamite_Channel%255DLittle_Girls_Blue_1978.mp4/file"
  },
  {
    "thumbnail": "https://images2.imgbox.com/a0/c9/giwG6bBe_o.jpeg",
    "title": "The Coming of Sin *vip",
    "info": "ယောကျာ်းဖြစ်သူဆုံးပီးတဲ့နောက်တစ်ယောက်တည်းနေလာတဲ့ Loranaတစ်နေ့တော့သူငယ်ချင်းဖြစ်သူSellies ရောက်လာပီး Triana ဆိုတဲ့ကောင်မလေးကိုလာအပ်သွားတယ်အဲ့ Triana ဆိုတဲ့ကောင်မလေးကမြင်းနဲ့လူကိုကြောက်တယ်ဆိုတဲ့အိမ်မက်ဆိုးကြောင့်ယောကျာ်းတွေကိုကြောက်လန့်နေတယ်.တစ်နေ့တော့မြင်းနဲ့လူတစ်ယောက်Lorana တို့အိမ်နားကိုရောက်ပီးဘာတေဆက်ဖြစ်ကြမလဲ..?.အဲ့မြင်းနဲ့လူကဘယ်သူလဲ?Triana ရဲ့အိမ်မက်ဆိုးနဲ့ဘာတွေပတ်သတ်နေတာလဲဆိုတာကတော့ The Coming of Sin ဇာတ်ကားမှစောင့်ကြည့်လိုက်ပါ",
    "url": "https://www.mediafire.com/file/5tu191mjp5nf0zc/%255BDynamite_Channel%255DThe_Coming_of_Sin.mp4/file"
  },
  {
    "thumbnail": "https://d1e9dm5cargh2w.cloudfront.net/images/ivd_large_front_image/297844.jpg",
    "title": "Flesh Digital Playground *vip",
    "info": "နာမည်ကြီးသရုပ်ဆောင်တွေစုစည်းရိုက်ကူးထားတဲ့ အမိုက်စား ဇတ်ကားပါပဲ  BDSMသမားတွေအကြိုက် ကြိုးတုပ်ခန်းတွေလဲအများကြီးထည့်ပေးထားပါတယ် Video Runtime 4:25:23 ဆိုတော့ တစ်ဝကြီးကြည့်ရမှာပါ sex ခန်း ၉ခန်းထိ့ပါဝင်ထားပါတယ်",
    "url": "https://www.mediafire.com/file/9gu6uw97eksj7rp/Flesh_Aung_Thiha_messsenger_gp.mp4/file"
  },
  {
    "thumbnail": "https://i0.wp.com/mangoporn.net/adult/wp-content/uploads/2021/03/Swingers-Getaway.jpg",
    "title": "Swingers Getaway vol1 *vip",
    "info": "Starring  Leah Gotti. Jenna Sativa. Gia Paige. James Deen. Kimmy Granger. Seth Gamble. Sophia Leone. Damon DiceDirector.James Avalon",
    "url": "https://www.mediafire.com/file/aajsjvyy7jgin5m/Swingers_Getaway_Vol._1_%25282016%2529Aung_Thiha_Messenger_gp.mp4/file"
  },
  {
    "thumbnail": "https://m.media-amazon.com/images/M/MV5BOGNhMmRlMjctMTk3YS00MDRmLTk2MTUtOTE5M2NiMDJlZWE3XkEyXkFqcGdeQXVyNTM3MDMyMDQ@._V1_.jpg",
    "title": "Bikini Jones And The Temple Of Eros mmsub *vip",
    "info": "မြန်မာစာတန်းထိုး တချို့ကြငွေကြေးဥစ္စာကြောင့်လူမဆန်တဲ့လုပ်ရပ်တွေလုပ်လာကြတယ်တစ်ချို့ကြအာဏာစည်းစိမ်တွေအတွက်အမှောင်လောကသားတွေဖြစ်သွားခဲ့ကြတယ်ဒီဇာတ်လမ်းထဲမှာတော့Triana of Aisha ကိုရတဲ့သူဟာMoriana ရဲ့ဘုရင်မဖြစ်မဲ့သူပါ.Dr.Jones တစ်ယောက်Triana of Aisha ကိုလိုက်ရှာတဲ့ခရီးမှာဘယ်လ်ိုအခက်အခဲတွေကြုံရမလဲ?...ဘယ်ဇာတ်ကောင်ကရောဘုရင်မဖြစ်သွားမှာလဲ?...အခုပြောနေတဲ့ပစ္စည်းကရောဘယ်လိုအရာများဖြစ်နေမလဲ?....ဆိုတာကိုတော့ဒီကားမှာဟာသဆန်ဆန်ရိုက်ကူးဖော်ပြထားပါတယ်...",
    "url": "https://www.mediafire.com/file/riilm3103t9eldl/%255BDynamite_Channel%255DBikini_Jones_And_The_Temple_Of_Eros_%25282010%2529.mp4/file"
  },
  {
    "thumbnail": "https://s7.dpic.me/02081/qu21db43pvme.jpg",
    "title": "Tarzan mmsub *vip",
    "info": "လူတွေကသူတို့မလုပ်ဖူးတဲ့အရာမသွားဖူးတဲ့နေရာတွေကိုသွားပြီးတော့လေ့လာစူးစမ်းချင်ကြတာသဘာဝလိုပါဘဲ,ဒီဇာတ်လမ်းမှာတစ်ချိန်ကခရီးသွားအုပ်စုတစ်စု‌သူတို့နဲ့မရင်နှီးတဲ့တောထဲကိုစူးစမ်းရှာဖွေဖို့အတွက်ထွက်လာခဲ့ကြပါတယ်,သူတို့တွေကသဘာဝဘေးအန္တရာယ်တွေနဲ့တောကောင်တွေရဲ့ရန်ကိုတော့ကြိုတွက်ပြီးပြင်ဆင်ထားခဲ့ပေမဲ့'တာဇ'ဆိုတဲ့မျိုးစိတ်နဲ့ပတ်သက်ပြီးမြင်ဖူးသူလဲမရှိတဲ့အတွက်ပြင်ဆင်မှုတွေမလုပ်လာခဲ့ပါဘူး,အဲ့တော့ခရီးသွားတဲ့လူတွေကရောသူတို့စိမ်းတဲ့တောထဲမှာဘာတွေတွေ့ကြုံရမလဲ...?တာဇံအနေနဲ့ကရောသူနဲ့မတူဘဲကွဲပြားနေတဲ့မိန်းမခန္ဓာကိုယ်ကိုတွေ့တဲ့အခါဘယ်လိုတုန့်ပြန်မလဲ?....ဆိုတာကိုတော့ဒီဇာတ်လမ်းမှာအမှောင်ဆန်ဆန်အားရပါးရကြည့်ရှုခံစားကြပါခင်ဗျာ...မြန်မာစာတန်းထိုး",
    "url": "https://www.mediafire.com/file/0xkrrfpysinfoyg/%255BDynamite_Channel%255DTarzan-X_Shame_of_Jane.mp4/file"
  },
  {
    "thumbnail": "https://imgs1cdn.adultempire.com/products/21/2602221h.jpg",
    "title": "He Made Her Squirt Digital Sin *vip",
    "info": "Abella Danger fan တွေရှိကြလားStarring  Abella Danger. AJ Applegate. Gina Valentina. Steve Holmes. Luna Star. James Deen. Ramon Nomar. Veronica Rodriguez. Chad WhiteDirector.  Eddie Powell",
    "url": "https://www.mediafire.com/file/jyxslp0wvynjrjy/He_Made_Her_Sq%2A%2Art.mp4/file"
  },
  {
    "thumbnail": "https://image.hotmovies.com/image2/xfront/245/245496.xfront.0.jpg",
    "title": "Love Stories Vol 1 *vip",
    "info": "Dani Daniels. Tyler Nixon. James Deen. Maddy  Reilly .Seth Gamble. Logan Pierce. Presley Hart. Kimber DayDirector. Mason",
    "url": "https://www.mediafire.com/file/j7h4sscmfycuony/Love_Stories_Vol._1_%25282013%2529.mp4/file"
  },
  {
    "thumbnail": "https://m.media-amazon.com/images/I/51j4lFTJmIL._AC_SY580_.jpg",
    "title": "Submission Of Emma Marx The Boundaries *vip",
    "info": "New Sensations - Romance Series 2016 AVN Award Winners XBIZ Award Winners - 2016ဇတ်လမ်းအညွှန်းတော့မရေးတော့ဘူး 2015မှာ နမည်ကြီးခဲ့တ့ဲ လူကြိုက်များ ဆုံး ဇတ်ကားအဖြစ်ရပ်တည်နိင်ခ့ဲပါတယ်",
    "url": "https://www.mediafire.com/file/kk91j7enl7f47ft/The_Submission_Of_Emma_Marx_Boundaries_%25282015%2529Aung_Thiha_Messenger_gp.mp4/file"
  },
  {
    "thumbnail": "https://i1.wp.com/xxxscenes.net/xxxmovies/wp-content/uploads/2021/03/9839837.jpg?fit=397%2C565&ssl=1",
    "title": "Restrant2 *vip",
    "info": " ဖိုင်ဆိုဒ် 777 mb",
    "url": "https://www.mediafire.com/file/zlxfy9xc5odlj8y/Restraint_Vol._2_%25282015%2529Aung_Thiha_Messenger_gp.mp4/file"
  },
  {
    "thumbnail": "https://imgs1cdn.adultempire.com/products/14/2723714h.jpg",
    "title": "Sibling Rivalry *vip",
    "info": "ဖိုင်ဆိုဒ်1.4gb ကြာချိန် 2 နာရီ",
    "url": "https://45.mangovideo.pw/contents/videos//48000/48097/48097.mp4"
  },
  {
    "thumbnail": "https://imgs1cdn.adultempire.com/products/76/2705376h.jpg",
    "title": "Forbidden Family Affairs *vip",
    "info": "ဖိုင်ဆိုဒ် 728mb ကြာချိန် 1နာရီ41မီနစ်",
    "url": "https://45.mangovideo.pw/contents/videos//29000/29457/29457.mp4"
  },
  {
    "thumbnail": "https://www.themoviedb.org/t/p/w220_and_h330_face/8YQHbEfznTBjSyMqsEZNKwWjZkN.jpg",
    "title": "Keep Your Family Close *vip",
    "info": "ဖိုင်ဆိုဒ်1.2 gb ကြာချိန် 2 နာရီ ",
    "url": "http://s10.mangovideo.pw/contents/videos/29000/29439/29439.mp4"
  },
  {
    "thumbnail": "https://imgs1cdn.adultempire.com/products/41/3113241h.jpg",
    "title": "Don’t Break Me 25 *vip",
    "info": "ဖိုင်ဆိုဒ် 1.5 gb ကြာချိန် 2 နာရီ",
    "url": "https://234.mangovideo.pw/contents/videos/37000/37706/37706.mp4"
  },
  {
    "thumbnail": "https://imgs1cdn.adultempire.com/products/48/2682148h.jpg",
    "title": "School Girls Gone Black 4 *vip",
    "info": "ဖိုင်ဆိုဒ် 2 gb ကြာချိန်2 နာရီ",
    "url": "https://s10.mangovideo.pw/contents/videos/24000/24563/24563.mp4"
  },
  {
    "thumbnail": "https://imgs1cdn.adultempire.com/products/09/2570909h.jpg",
    "title": "Lex Loves Teens *vip",
    "info": "ဖိုင်ဆိုဒ် 1.5 gb ကြာချိန် 5 နာရီ",
    "url": "https://s10.mangovideo.pw/contents/videos/2000/2455/2455.mp4"
  }
]